MANIFEST.in
README.md
setup.cfg
setup.py
versioneer.py
examples/__init__.py
examples/file-chooser.ui
examples/filemanager.ui
examples/multi-spindle.ui
examples/python_only_vcp.py
examples/status-labels.ui
examples/tool-table.ui
examples/actions/__init__.py
examples/actions/config.yml
examples/actions/ui/mainwindow.ui
examples/actions/ui/style.qss
examples/brender/__init__.py
examples/brender/brender.py
examples/brender/brender.yml
examples/brender/resources/brender.qrc
examples/brender/resources/brender.qss
examples/brender/resources/images/button.png
examples/brender/resources/images/checkbox_checked.png
examples/brender/resources/images/checkbox_checked_hover.png
examples/brender/resources/images/checkbox_checked_pressed.png
examples/brender/resources/images/checkbox_unchecked.png
examples/brender/resources/images/checkbox_unchecked_hover.png
examples/brender/resources/images/checkbox_unchecked_pressed.png
examples/brender/resources/images/down_arrow.png
examples/brender/resources/images/down_arrow_disabled.png
examples/brender/resources/images/frame.png
examples/brender/resources/images/pagefold.png
examples/brender/resources/images/pp_border.png
examples/brender/resources/images/probe.png
examples/brender/resources/images/pushbutton.png
examples/brender/resources/images/pushbutton_hover.png
examples/brender/resources/images/pushbutton_pressed.png
examples/brender/resources/images/radiobutton_checked.png
examples/brender/resources/images/radiobutton_checked_hover.png
examples/brender/resources/images/radiobutton_checked_pressed.png
examples/brender/resources/images/radiobutton_unchecked.png
examples/brender/resources/images/radiobutton_unchecked_hover.png
examples/brender/resources/images/radiobutton_unchecked_pressed.png
examples/brender/resources/images/sizegrip.png
examples/brender/resources/images/spindown.png
examples/brender/resources/images/spindown_hover.png
examples/brender/resources/images/spindown_off.png
qtpyvcp.egg-info/PKG-INFO
qtpyvcp.egg-info/SOURCES.txt
qtpyvcp.egg-info/dependency_links.txt
qtpyvcp.egg-info/entry_points.txt
qtpyvcp.egg-info/requires.txt
qtpyvcp.egg-info/top_level.txt
