Metadata-Version: 2.1
Name: qtpyvcp
Version: 0.3.19
Summary: Qt and Python based Virtual Control Panel framework for LinuxCNC.
Home-page: https://github.com/kcjengr/qtpyvcp
Author: Kurt Jacobson
Author-email: kcjengr@gmail.com
License: GNU General Public License v2 (GPLv2)
Download-URL: https://github.com/kcjengr/qtpyvcp/archive/master.zip
Platform: UNKNOWN
Classifier: Development Status :: 3 - Alpha
Classifier: Intended Audience :: Developers
Classifier: Intended Audience :: Manufacturing
Classifier: Intended Audience :: End Users/Desktop
Classifier: Topic :: Software Development :: Widget Sets
Classifier: Topic :: Software Development :: User Interfaces
Classifier: License :: OSI Approved :: GNU General Public License v2 (GPLv2)
Classifier: Programming Language :: Python :: 2.7
